[
  {
    "names": {
      "kk": "Қазақ тілі мен әдебиеті 1",
      "ru": "Қазақ тілі мен әдебиеті 1"
    },
    "group": "7",
    "image": "https://books.okulyk.kz/1507/1507.jpg",
    "pdf_url": "https://books.okulyk.kz/1507/1507.pdf",
    "preview_page": "",
    "language": "kk"
  },
  {
    "names": {
      "kk": "Қазақ тілі мен әдебиеті 2",
      "ru": "Қазақ тілі мен әдебиеті 2"
    },
    "group": "7",
    "image": "https://books.okulyk.kz/1508/1508.jpg",
    "pdf_url": "https://books.okulyk.kz/1508/1508.pdf",
    "preview_page": "",
    "language": "kk"
  },
  {
    "names": {
      "kk": "Орыс тілі және әдебиеті",
      "ru": "Орыс тілі және әдебиеті"
    },
    "group": "7",
    "image": "https://books.okulyk.kz/236/236.jpg",
    "pdf_url": "https://books.okulyk.kz/236/236.pdf",
    "preview_page": "",
    "language": "kk"
  },
  {
    "names": {
      "kk": "Алгебра",
      "ru": "Алгебра"
    },
    "group": "7",
    "image": "https://books.okulyk.kz/239/239.jpg",
    "pdf_url": "https://books.okulyk.kz/239/239.pdf",
    "preview_page": "",
    "language": "kk"
  },
  {
    "names": {
      "kk": "Геометрия",
      "ru": "Геометрия"
    },
    "group": "7",
    "image": "https://books.okulyk.kz/240/240.jpg",
    "pdf_url": "https://books.okulyk.kz/240/240.pdf",
    "preview_page": "",
    "language": "kk"
  },
  {
    "names": {
      "kk": "География",
      "ru": "География"
    },
    "group": "7",
    "image": "https://books.okulyk.kz/243/243.jpg",
    "pdf_url": "https://books.okulyk.kz/243/243.pdf",
    "preview_page": "",
    "language": "kk"
  },
  {
    "names": {
      "kk": "Информатика",
      "ru": "Информатика"
    },
    "group": "7",
    "image": "https://books.okulyk.kz/241/241.jpg",
    "pdf_url": "https://books.okulyk.kz/241/241.pdf",
    "preview_page": "",
    "language": "kk"
  },
  {
    "names": {
      "kk": "Биология",
      "ru": "Биология"
    },
    "group": "7",
    "image": "https://books.okulyk.kz/246/246.jpg",
    "pdf_url": "https://books.okulyk.kz/246/246.pdf",
    "preview_page": "",
    "language": "kk"
  },
  {
    "names": {
      "kk": "Физика",
      "ru": "Физика"
    },
    "group": "7",
    "image": "https://books.okulyk.kz/247/247.jpg",
    "pdf_url": "https://books.okulyk.kz/247/247.pdf",
    "preview_page": "",
    "language": "kk"
  },
  {
    "names": {
      "kk": "Химия",
      "ru": "Химия"
    },
    "group": "7",
    "image": "https://books.okulyk.kz/249/249.jpg",
    "pdf_url": "https://books.okulyk.kz/249/249.pdf",
    "preview_page": "",
    "language": "kk"
  },
  {
    "names": {
      "kk": "Ағылшын тілі",
      "ru": "Ағылшын тілі"
    },
    "group": "7",
    "image": "https://books.okulyk.kz/286/286.jpg",
    "pdf_url": "https://books.okulyk.kz/286/286.pdf",
    "preview_page": "",
    "language": "kk"
  },
  {
    "names": {
      "kk": "Қазақстан тарихы",
      "ru": "Қазақстан тарихы"
    },
    "group": "7",
    "image": "https://books.okulyk.kz/317/317.jpg",
    "pdf_url": "https://books.okulyk.kz/317/317.pdf",
    "preview_page": "",
    "language": "kk"
  },
  {
    "names": {
      "kk": "Дүниежүзі тарихы",
      "ru": "Дүниежүзі тарихы"
    },
    "group": "7",
    "image": "https://books.okulyk.kz/319/319.jpg",
    "pdf_url": "https://books.okulyk.kz/319/319.pdf",
    "preview_page": "",
    "language": "kk"
  },
  {
    "names": {
      "kk": "Қазақ тілі мен әдебиеті 1",
      "ru": "Қазақ тілі мен әдебиеті 1"
    },
    "group": "8",
    "image": "https://books.okulyk.kz/768/768.jpg",
    "pdf_url": "https://books.okulyk.kz/768/768.pdf",
    "preview_page": "",
    "language": "kk"
  },
  {
    "names": {
      "kk": "Қазақ тілі мен әдебиеті 2",
      "ru": "Қазақ тілі мен әдебиеті 2"
    },
    "group": "8",
    "image": "https://books.okulyk.kz/769/769.jpg",
    "pdf_url": "https://books.okulyk.kz/769/769.pdf",
    "preview_page": "",
    "language": "kk"
  },
  {
    "names": {
      "kk": "Қазақ тілі",
      "ru": "Қазақ тілі"
    },
    "group": "8",
    "image": "https://books.okulyk.kz/290/290.jpg",
    "pdf_url": "https://books.okulyk.kz/290/290.pdf",
    "preview_page": "",
    "language": "kk"
  },
  {
    "names": {
      "kk": "Қазақ әдебиеті",
      "ru": "Қазақ әдебиеті"
    },
    "group": "8",
    "image": "https://books.okulyk.kz/293/293.jpg",
    "pdf_url": "https://books.okulyk.kz/293/293.pdf",
    "preview_page": "",
    "language": "kk"
  },
  {
    "names": {
      "kk": "Орыс тілі және әдебиеті",
      "ru": "Орыс тілі және әдебиеті"
    },
    "group": "8",
    "image": "https://books.okulyk.kz/298/298.jpg",
    "pdf_url": "https://books.okulyk.kz/298/298.pdf",
    "preview_page": "",
    "language": "kk"
  },
  {
    "names": {
      "kk": "Алгебра",
      "ru": "Алгебра"
    },
    "group": "8",
    "image": "https://books.okulyk.kz/300/300.jpg",
    "pdf_url": "https://books.okulyk.kz/300/300.pdf",
    "preview_page": "",
    "language": "kk"
  },
  {
    "names": {
      "kk": "Геометрия",
      "ru": "Геометрия"
    },
    "group": "8",
    "image": "https://books.okulyk.kz/303/303.jpg",
    "pdf_url": "https://books.okulyk.kz/303/303.pdf",
    "preview_page": "",
    "language": "kk"
  },
  {
    "names": {
      "kk": "Информатика",
      "ru": "Информатика"
    },
    "group": "8",
    "image": "https://books.okulyk.kz/306/306.jpg",
    "pdf_url": "https://books.okulyk.kz/306/306.pdf",
    "preview_page": "",
    "language": "kk"
  },
  {
    "names": {
      "kk": "География",
      "ru": "География"
    },
    "group": "8",
    "image": "https://books.okulyk.kz/310/310.jpg",
    "pdf_url": "https://books.okulyk.kz/310/310.pdf",
    "preview_page": "",
    "language": "kk"
  },
  {
    "names": {
      "kk": "Физика",
      "ru": "Физика"
    },
    "group": "8",
    "image": "https://books.okulyk.kz/313/313.jpg",
    "pdf_url": "https://books.okulyk.kz/313/313.pdf",
    "preview_page": "",
    "language": "kk"
  },
  {
    "names": {
      "kk": "Химия",
      "ru": "Химия"
    },
    "group": "8",
    "image": "https://books.okulyk.kz/316/316.jpg",
    "pdf_url": "https://books.okulyk.kz/316/316.pdf",
    "preview_page": "",
    "language": "kk"
  },
  {
    "names": {
      "kk": "Ағылшын тілі",
      "ru": "Ағылшын тілі"
    },
    "group": "8",
    "image": "https://books.okulyk.kz/362/362.jpg",
    "pdf_url": "https://books.okulyk.kz/362/362.pdf",
    "preview_page": "",
    "language": "kk"
  },
  {
    "names": {
      "kk": "Қазақстан тарихы",
      "ru": "Қазақстан тарихы"
    },
    "group": "8",
    "image": "https://books.okulyk.kz/409/409.jpg",
    "pdf_url": "https://books.okulyk.kz/409/409.pdf",
    "preview_page": "",
    "language": "kk"
  },
  {
    "names": {
      "kk": "Дүниежүзі тарихы",
      "ru": "Дүниежүзі тарихы"
    },
    "group": "8",
    "image": "https://books.okulyk.kz/413/413.jpg",
    "pdf_url": "https://books.okulyk.kz/413/413.pdf",
    "preview_page": "",
    "language": "kk"
  },
  {
    "names": {
      "kk": "Қазақ тілі мен әдебиеті 1",
      "ru": "Қазақ тілі мен әдебиеті 1"
    },
    "group": "9",
    "image": "https://books.okulyk.kz/431/431.jpg",
    "pdf_url": "https://books.okulyk.kz/431/431.pdf",
    "preview_page": "",
    "language": "kk"
  },
  {
    "names": {
      "kk": "Қазақ тілі мен әдебиеті 2",
      "ru": "Қазақ тілі мен әдебиеті 2"
    },
    "group": "9",
    "image": "https://books.okulyk.kz/432/432.jpg",
    "pdf_url": "https://books.okulyk.kz/432/432.pdf",
    "preview_page": "",
    "language": "kk"
  },
  {
    "names": {
      "kk": "Қазақ тілі",
      "ru": "Қазақ тілі"
    },
    "group": "9",
    "image": "https://books.okulyk.kz/374/374.jpg",
    "pdf_url": "https://books.okulyk.kz/374/374.pdf",
    "preview_page": "",
    "language": "kk"
  },
  {
    "names": {
      "kk": "Қазақ әдебиеті",
      "ru": "Қазақ әдебиеті"
    },
    "group": "9",
    "image": "https://books.okulyk.kz/376/376.jpg",
    "pdf_url": "https://books.okulyk.kz/376/376.pdf",
    "preview_page": "",
    "language": "kk"
  },
  {
    "names": {
      "kk": "Орыс тілі және әдебиеті 1",
      "ru": "Орыс тілі және әдебиеті 1"
    },
    "group": "9",
    "image": "https://books.okulyk.kz/380/380.jpg",
    "pdf_url": "https://books.okulyk.kz/380/380.pdf",
    "preview_page": "",
    "language": "kk"
  },
  {
    "names": {
      "kk": "Орыс тілі және әдебиеті 2",
      "ru": "Орыс тілі және әдебиеті 2"
    },
    "group": "9",
    "image": "https://books.okulyk.kz/381/381.jpg",
    "pdf_url": "https://books.okulyk.kz/381/381.pdf",
    "preview_page": "",
    "language": "kk"
  },
  {
    "names": {
      "kk": "Алгебра",
      "ru": "Алгебра"
    },
    "group": "9",
    "image": "https://books.okulyk.kz/385/385.jpg",
    "pdf_url": "https://books.okulyk.kz/385/385.pdf",
    "preview_page": "",
    "language": "kk"
  },
  {
    "names": {
      "kk": "Геометрия",
      "ru": "Геометрия"
    },
    "group": "9",
    "image": "https://books.okulyk.kz/389/389.jpg",
    "pdf_url": "https://books.okulyk.kz/389/389.pdf",
    "preview_page": "",
    "language": "kk"
  },
  {
    "names": {
      "kk": "Информатика",
      "ru": "Информатика"
    },
    "group": "9",
    "image": "https://books.okulyk.kz/392/392.jpg",
    "pdf_url": "https://books.okulyk.kz/392/392.pdf",
    "preview_page": "",
    "language": "kk"
  },
  {
    "names": {
      "kk": "География 1",
      "ru": "География 1"
    },
    "group": "9",
    "image": "https://books.okulyk.kz/396/396.jpg",
    "pdf_url": "https://books.okulyk.kz/396/396.pdf",
    "preview_page": "",
    "language": "kk"
  },
  {
    "names": {
      "kk": "География 2",
      "ru": "География 2"
    },
    "group": "9",
    "image": "https://books.okulyk.kz/397/397.jpg",
    "pdf_url": "https://books.okulyk.kz/397/397.pdf",
    "preview_page": "",
    "language": "kk"
  },
  {
    "names": {
      "kk": "Физика",
      "ru": "Физика"
    },
    "group": "9",
    "image": "https://books.okulyk.kz/404/404.jpg",
    "pdf_url": "https://books.okulyk.kz/404/404.pdf",
    "preview_page": "",
    "language": "kk"
  },
  {
    "names": {
      "kk": "Химия 1",
      "ru": "Химия 1"
    },
    "group": "9",
    "image": "https://books.okulyk.kz/406/406.jpg",
    "pdf_url": "https://books.okulyk.kz/406/406.pdf",
    "preview_page": "",
    "language": "kk"
  },
  {
    "names": {
      "kk": "Химия 2",
      "ru": "Химия 2"
    },
    "group": "9",
    "image": "https://books.okulyk.kz/407/407.jpg",
    "pdf_url": "https://books.okulyk.kz/407/407.pdf",
    "preview_page": "",
    "language": "kk"
  },
  {
    "names": {
      "kk": "Қазақстан тарихы 1",
      "ru": "Қазақстан тарихы 1"
    },
    "group": "9",
    "image": "https://books.okulyk.kz/409/409.jpg",
    "pdf_url": "https://books.okulyk.kz/409/409.pdf",
    "preview_page": "",
    "language": "kk"
  },
  {
    "names": {
      "kk": "Қазақстан тарихы 2",
      "ru": "Қазақстан тарихы 2"
    },
    "group": "9",
    "image": "https://books.okulyk.kz/410/410.jpg",
    "pdf_url": "https://books.okulyk.kz/410/410.pdf",
    "preview_page": "",
    "language": "kk"
  },
  {
    "names": {
      "kk": "Дүниежүзі тарихы 1",
      "ru": "Дүниежүзі тарихы 1"
    },
    "group": "9",
    "image": "https://books.okulyk.kz/413/413.jpg",
    "pdf_url": "https://books.okulyk.kz/413/413.pdf",
    "preview_page": "",
    "language": "kk"
  },
  {
    "names": {
      "kk": "Дүниежүзі тарихы 2",
      "ru": "Дүниежүзі тарихы 2"
    },
    "group": "9",
    "image": "https://books.okulyk.kz/414/414.jpg",
    "pdf_url": "https://books.okulyk.kz/414/414.pdf",
    "preview_page": "",
    "language": "kk"
  },
  {
    "names": {
      "kk": "Құқық",
      "ru": "Құқық"
    },
    "group": "9",
    "image": "https://books.okulyk.kz/415/415.jpg",
    "pdf_url": "https://books.okulyk.kz/415/415.pdf",
    "preview_page": "",
    "language": "kk"
  },
  {
    "names": {
      "kk": "Ағылшын тілі",
      "ru": "Ағылшын тілі"
    },
    "group": "9",
    "image": "https://books.okulyk.kz/469/469.jpg",
    "pdf_url": "https://books.okulyk.kz/469/469.pdf",
    "preview_page": "",
    "language": "kk"
  },
  {
    "names": {
      "kk": "Қазақ тілі мен әдебиеті 1",
      "ru": "Қазақ тілі мен әдебиеті 1"
    },
    "group": "10",
    "image": "https://books.okulyk.kz/607/607.jpg",
    "pdf_url": "https://books.okulyk.kz/607/607.pdf",
    "preview_page": "",
    "language": "kk"
  },
  {
    "names": {
      "kk": "Қазақ тілі мен әдебиеті 2",
      "ru": "Қазақ тілі мен әдебиеті 2"
    },
    "group": "10",
    "image": "https://books.okulyk.kz/608/608.jpg",
    "pdf_url": "https://books.okulyk.kz/608/608.pdf",
    "preview_page": "",
    "language": "kk"
  },
  {
    "names": {
      "kk": "Қазақ тілі 1",
      "ru": "Қазақ тілі 1"
    },
    "group": "10",
    "image": "https://books.okulyk.kz/484/484.jpg",
    "pdf_url": "https://books.okulyk.kz/484/484.pdf",
    "preview_page": "",
    "language": "kk"
  },
  {
    "names": {
      "kk": "Қазақ тілі 2",
      "ru": "Қазақ тілі 2"
    },
    "group": "10",
    "image": "https://books.okulyk.kz/487/487.jpg",
    "pdf_url": "https://books.okulyk.kz/487/487.pdf",
    "preview_page": "",
    "language": "kk"
  },
  {
    "names": {
      "kk": "Алгебра",
      "ru": "Алгебра"
    },
    "group": "10",
    "image": "https://books.okulyk.kz/491/491.jpg",
    "pdf_url": "https://books.okulyk.kz/491/491.pdf",
    "preview_page": "",
    "language": "kk"
  },
  {
    "names": {
      "kk": "Геометрия",
      "ru": "Геометрия"
    },
    "group": "10",
    "image": "https://books.okulyk.kz/493/493.jpg",
    "pdf_url": "https://books.okulyk.kz/493/493.pdf",
    "preview_page": "",
    "language": "kk"
  },
  {
    "names": {
      "kk": "Информатика",
      "ru": "Информатика"
    },
    "group": "10",
    "image": "https://books.okulyk.kz/497/497.jpg",
    "pdf_url": "https://books.okulyk.kz/497/497.pdf",
    "preview_page": "",
    "language": "kk"
  },
  {
    "names": {
      "kk": "География",
      "ru": "География"
    },
    "group": "10",
    "image": "https://books.okulyk.kz/498/498.jpg",
    "pdf_url": "https://books.okulyk.kz/498/498.pdf",
    "preview_page": "",
    "language": "kk"
  },
  {
    "names": {
      "kk": "Физика 1",
      "ru": "Физика 1"
    },
    "group": "10",
    "image": "https://books.okulyk.kz/503/503.jpg",
    "pdf_url": "https://books.okulyk.kz/503/503.pdf",
    "preview_page": "",
    "language": "kk"
  },
  {
    "names": {
      "kk": "Физика 2",
      "ru": "Физика 2"
    },
    "group": "10",
    "image": "https://books.okulyk.kz/504/504.jpg",
    "pdf_url": "https://books.okulyk.kz/504/504.pdf",
    "preview_page": "",
    "language": "kk"
  },
  {
    "names": {
      "kk": "Химия 1",
      "ru": "Химия 1"
    },
    "group": "10",
    "image": "https://books.okulyk.kz/506/506.jpg",
    "pdf_url": "https://books.okulyk.kz/506/506.pdf",
    "preview_page": "",
    "language": "kk"
  },
  {
    "names": {
      "kk": "Химия 2",
      "ru": "Химия 2"
    },
    "group": "10",
    "image": "https://books.okulyk.kz/507/507.jpg",
    "pdf_url": "https://books.okulyk.kz/507/507.pdf",
    "preview_page": "",
    "language": "kk"
  },
  {
    "names": {
      "kk": "Дүниежүзі тарихы 1",
      "ru": "Дүниежүзі тарихы 1"
    },
    "group": "10",
    "image": "https://books.okulyk.kz/508/508.jpg",
    "pdf_url": "https://books.okulyk.kz/508/508.pdf",
    "preview_page": "",
    "language": "kk"
  },
  {
    "names": {
      "kk": "Дүниежүзі тарихы 2",
      "ru": "Дүниежүзі тарихы 2"
    },
    "group": "10",
    "image": "https://books.okulyk.kz/509/509.jpg",
    "pdf_url": "https://books.okulyk.kz/509/509.pdf",
    "preview_page": "",
    "language": "kk"
  },
  {
    "names": {
      "kk": "Құқық",
      "ru": "Құқық"
    },
    "group": "10",
    "image": "https://books.okulyk.kz/510/510.jpg",
    "pdf_url": "https://books.okulyk.kz/510/510.pdf",
    "preview_page": "",
    "language": "kk"
  },
  {
    "names": {
      "kk": "Алғашқы әскери дайындық 1",
      "ru": "Алғашқы әскери дайындық 1"
    },
    "group": "10",
    "image": "https://books.okulyk.kz/599/599.jpg",
    "pdf_url": "https://books.okulyk.kz/599/599.pdf",
    "preview_page": "",
    "language": "kk"
  },
  {
    "names": {
      "kk": "Алғашқы әскери дайындық 2",
      "ru": "Алғашқы әскери дайындық 2"
    },
    "group": "10",
    "image": "https://books.okulyk.kz/600/600.jpg",
    "pdf_url": "https://books.okulyk.kz/600/600.pdf",
    "preview_page": "",
    "language": "kk"
  },
  {
    "names": {
      "kk": "Қазақстан тарихы",
      "ru": "Қазақстан тарихы"
    },
    "group": "10",
    "image": "https://books.okulyk.kz/595/595.jpg",
    "pdf_url": "https://books.okulyk.kz/595/595.pdf",
    "preview_page": "",
    "language": "kk"
  },
  {
    "names": {
      "kk": "Орыс тілі",
      "ru": "Орыс тілі"
    },
    "group": "10",
    "image": "https://books.okulyk.kz/592/592.jpg",
    "pdf_url": "https://books.okulyk.kz/592/592.pdf",
    "preview_page": "",
    "language": "kk"
  },
  {
    "names": {
      "kk": "Ағылшын тілі",
      "ru": "Ағылшын тілі"
    },
    "group": "10",
    "image": "https://books.okulyk.kz/535/535.jpg",
    "pdf_url": "https://books.okulyk.kz/535/535.pdf",
    "preview_page": "",
    "language": "kk"
  },
  {
    "names": {
      "kk": "Қазақ тілі мен әдебиеті 1",
      "ru": "Қазақ тілі мен әдебиеті 1"
    },
    "group": "11",
    "image": "https://books.okulyk.kz/790/790.jpg",
    "pdf_url": "https://books.okulyk.kz/790/790.pdf",
    "preview_page": "",
    "language": "kk"
  },
  {
    "names": {
      "kk": "Қазақ тілі мен әдебиеті 2",
      "ru": "Қазақ тілі мен әдебиеті 2"
    },
    "group": "11",
    "image": "https://books.okulyk.kz/791/791.jpg",
    "pdf_url": "https://books.okulyk.kz/791/791.pdf",
    "preview_page": "",
    "language": "kk"
  },
  {
    "names": {
      "kk": "Қазақ тілі",
      "ru": "Қазақ тілі"
    },
    "group": "11",
    "image": "https://books.okulyk.kz/781/781.jpg",
    "pdf_url": "https://books.okulyk.kz/781/781.pdf",
    "preview_page": "",
    "language": "kk"
  },
  {
    "names": {
      "kk": "Қазақ әдебиеті",
      "ru": "Қазақ әдебиеті"
    },
    "group": "11",
    "image": "https://books.okulyk.kz/785/785.jpg",
    "pdf_url": "https://books.okulyk.kz/785/785.pdf",
    "preview_page": "",
    "language": "kk"
  },
  {
    "names": {
      "kk": "Дүниежүзі тарих",
      "ru": "Дүниежүзі тарих"
    },
    "group": "11",
    "image": "https://books.okulyk.kz/670/670.jpg",
    "pdf_url": "https://books.okulyk.kz/670/670.pdf",
    "preview_page": "",
    "language": "kk"
  },
  {
    "names": {
      "kk": "География",
      "ru": "География"
    },
    "group": "11",
    "image": "https://books.okulyk.kz/672/672.jpg",
    "pdf_url": "https://books.okulyk.kz/672/672.pdf",
    "preview_page": "",
    "language": "kk"
  },
  {
    "names": {
      "kk": "Құқық негізі",
      "ru": "Құқық негізі"
    },
    "group": "11",
    "image": "https://books.okulyk.kz/675/675.jpg",
    "pdf_url": "https://books.okulyk.kz/675/675.pdf",
    "preview_page": "",
    "language": "kk"
  },
  {
    "names": {
      "kk": "Физика 1",
      "ru": "Физика 1"
    },
    "group": "11",
    "image": "https://books.okulyk.kz/677/677.jpg",
    "pdf_url": "https://books.okulyk.kz/677/677.pdf",
    "preview_page": "",
    "language": "kk"
  },
  {
    "names": {
      "kk": "Химия 1",
      "ru": "Химия 1"
    },
    "group": "11",
    "image": "https://books.okulyk.kz/679/679.jpg",
    "pdf_url": "https://books.okulyk.kz/679/679.pdf",
    "preview_page": "",
    "language": "kk"
  },
  {
    "names": {
      "kk": "Биология 1",
      "ru": "Биология 1"
    },
    "group": "11",
    "image": "https://books.okulyk.kz/700/700.jpg",
    "pdf_url": "https://books.okulyk.kz/700/700.pdf",
    "preview_page": "",
    "language": "kk"
  },
  {
    "names": {
      "kk": "Физика 2",
      "ru": "Физика 2"
    },
    "group": "11",
    "image": "https://books.okulyk.kz/707/707.jpg",
    "pdf_url": "https://books.okulyk.kz/707/707.pdf",
    "preview_page": "",
    "language": "kk"
  },
  {
    "names": {
      "kk": "Химия 2",
      "ru": "Химия 2"
    },
    "group": "11",
    "image": "https://books.okulyk.kz/708/708.jpg",
    "pdf_url": "https://books.okulyk.kz/708/708.pdf",
    "preview_page": "",
    "language": "kk"
  },
  {
    "names": {
      "kk": "Биология 2",
      "ru": "Биология 2"
    },
    "group": "11",
    "image": "https://books.okulyk.kz/712/712.jpg",
    "pdf_url": "https://books.okulyk.kz/712/712.pdf",
    "preview_page": "",
    "language": "kk"
  },
  {
    "names": {
      "kk": "Алғашқы әскери дайындық 1",
      "ru": "Алғашқы әскери дайындық 1"
    },
    "group": "11",
    "image": "https://books.okulyk.kz/735/735.jpg",
    "pdf_url": "https://books.okulyk.kz/735/735.pdf",
    "preview_page": "",
    "language": "kk"
  },
  {
    "names": {
      "kk": "Алғашқы әскери дайындық 2",
      "ru": "Алғашқы әскери дайындық 2"
    },
    "group": "11",
    "image": "https://books.okulyk.kz/736/736.jpg",
    "pdf_url": "https://books.okulyk.kz/736/736.pdf",
    "preview_page": "",
    "language": "kk"
  },
  {
    "names": {
      "kk": "Алгебра 1",
      "ru": "Алгебра 1"
    },
    "group": "11",
    "image": "https://books.okulyk.kz/777/777.jpg",
    "pdf_url": "https://books.okulyk.kz/777/777.pdf",
    "preview_page": "",
    "language": "kk"
  },
  {
    "names": {
      "kk": "Алгебра 2",
      "ru": "Алгебра 2"
    },
    "group": "11",
    "image": "https://books.okulyk.kz/778/778.jpg",
    "pdf_url": "https://books.okulyk.kz/778/778.pdf",
    "preview_page": "",
    "language": "kk"
  },
  {
    "names": {
      "kk": "Геометрия",
      "ru": "Геометрия"
    },
    "group": "11",
    "image": "https://books.okulyk.kz/815/815.jpg",
    "pdf_url": "https://books.okulyk.kz/815/815.pdf",
    "preview_page": "",
    "language": "kk"
  },
  {
    "names": {
      "kk": "Ағылшын тілі (SB)",
      "ru": "Ағылшын тілі (SB)"
    },
    "group": "11",
    "image": "https://books.okulyk.kz/829/829.jpg",
    "pdf_url": "https://books.okulyk.kz/829/829.pdf",
    "preview_page": "",
    "language": "kk"
  },
  {
    "names": {
      "kk": "Қазақстан тарихы 1",
      "ru": "Қазақстан тарихы 1"
    },
    "group": "11",
    "image": "https://books.okulyk.kz/818/818.jpg",
    "pdf_url": "https://books.okulyk.kz/818/818.pdf",
    "preview_page": "",
    "language": "kk"
  },
  {
    "names": {
      "kk": "Қазақстан тарихы 2",
      "ru": "Қазақстан тарихы 2"
    },
    "group": "11",
    "image": "https://books.okulyk.kz/819/819.jpg",
    "pdf_url": "https://books.okulyk.kz/819/819.pdf",
    "preview_page": "",
    "language": "kk"
  },
  {
    "names": {
      "kk": "Омар М.",
      "ru": "Омар М."
    },
    "group": "geometry",
    "image": "https://i.ibb.co.com/gwggrJq/1.png",
    "pdf_url": "https://pub-6b4913ff96fe4b018ce574d6efc28d60.r2.dev/1.pdf",
    "preview_page": "https://i.ibb.co.com/gwggrJq/1.png",
    "language": "ru"
  },
  {
    "names": {
      "kk": "Потоскуев 10",
      "ru": "Потоскуев 10"
    },
    "group": "geometry",
    "image": "https://i.ibb.co.com/vP6vQjp/6.png",
    "pdf_url": "https://pub-6b4913ff96fe4b018ce574d6efc28d60.r2.dev/6.pdf",
    "preview_page": "https://i.ibb.co.com/vP6vQjp/6.png",
    "language": "ru"
  },
  {
    "names": {
      "kk": "Шар и сфера",
      "ru": "Шар и сфера"
    },
    "group": "geometry",
    "image": "https://i.ibb.co.com/HTTC0GK/15.png",
    "pdf_url": "https://pub-6b4913ff96fe4b018ce574d6efc28d60.r2.dev/15.pdf",
    "preview_page": "https://i.ibb.co.com/HTTC0GK/15.png",
    "language": "ru"
  },
  {
    "names": {
      "kk": "Потоскуев 11",
      "ru": "Потоскуев 11"
    },
    "group": "geometry",
    "image": "https://i.ibb.co.com/NYRrQXz/19.png",
    "pdf_url": "https://pub-6b4913ff96fe4b018ce574d6efc28d60.r2.dev/19.pdf",
    "preview_page": "https://i.ibb.co.com/NYRrQXz/19.png",
    "language": "ru"
  },
  {
    "names": {
      "kk": "Будак",
      "ru": "Будак"
    },
    "group": "geometry",
    "image": "https://i.ibb.co/fMckzgm/20.png",
    "pdf_url": "https://pub-6b4913ff96fe4b018ce574d6efc28d60.r2.dev/20.pdf",
    "preview_page": "https://i.ibb.co/fMckzgm/20.png",
    "language": "ru"
  },
  {
    "names": {
      "kk": "Зив 7-11",
      "ru": "Зив 7-11"
    },
    "group": "geometry",
    "image": "https://i.ibb.co/WxvxxTz/21.png",
    "pdf_url": "https://pub-6b4913ff96fe4b018ce574d6efc28d60.r2.dev/21.pdf",
    "preview_page": "https://i.ibb.co/WxvxxTz/21.png",
    "language": "ru"
  },
  {
    "names": {
      "kk": "Звавич 8-11",
      "ru": "Звавич 8-11"
    },
    "group": "geometry",
    "image": "https://i.ibb.co/sHKMbJq/22.png",
    "pdf_url": "https://pub-6b4913ff96fe4b018ce574d6efc28d60.r2.dev/22.pdf",
    "preview_page": "https://i.ibb.co/sHKMbJq/22.png",
    "language": "ru"
  },
  {
    "names": {
      "kk": "Казаков 10",
      "ru": "Казаков 10"
    },
    "group": "geometry",
    "image": "https://i.ibb.co/60W06x5/23.png",
    "pdf_url": "https://pub-6b4913ff96fe4b018ce574d6efc28d60.r2.dev/23.pdf",
    "preview_page": "https://i.ibb.co/60W06x5/23.png",
    "language": "ru"
  },
  {
    "names": {
      "kk": "Ломоносова 6",
      "ru": "Ломоносова 6"
    },
    "group": "geometry",
    "image": "https://i.ibb.co/N13qqs2/31.png",
    "pdf_url": "https://pub-6b4913ff96fe4b018ce574d6efc28d60.r2.dev/31.pdf",
    "preview_page": "https://i.ibb.co/N13qqs2/31.png",
    "language": "ru"
  },
  {
    "names": {
      "kk": "Потоскуев Оқулық 10 (1)",
      "ru": "Потоскуев Оқулық 10 (1)"
    },
    "group": "geometry",
    "image": "https://i.ibb.co/xMBP1Nx/34.png",
    "pdf_url": "https://pub-6b4913ff96fe4b018ce574d6efc28d60.r2.dev/34.pdf",
    "preview_page": "https://i.ibb.co/xMBP1Nx/34.png",
    "language": "kk"
  },
  {
    "names": {
      "kk": "Потоскуев Оқулық 10 (2)",
      "ru": "Потоскуев Оқулық 10 (2)"
    },
    "group": "geometry",
    "image": "https://i.ibb.co/JvQ4cyV/35.png",
    "pdf_url": "https://pub-6b4913ff96fe4b018ce574d6efc28d60.r2.dev/35.pdf",
    "preview_page": "https://i.ibb.co/JvQ4cyV/35.png",
    "language": "kk"
  },
  {
    "names": {
      "kk": "Яковлев",
      "ru": "Яковлев"
    },
    "group": "geometry",
    "image": "https://i.ibb.co.com/Wf26MW1/41.png",
    "pdf_url": "https://pub-6b4913ff96fe4b018ce574d6efc28d60.r2.dev/41.pdf",
    "preview_page": "https://i.ibb.co.com/Wf26MW1/41.png",
    "language": "ru"
  },
  {
    "names": {
      "kk": "Зив 10-11",
      "ru": "Зив 10-11"
    },
    "group": "algebra",
    "image": "https://i.ibb.co.com/sb7rrPB/2.png",
    "pdf_url": "https://pub-6b4913ff96fe4b018ce574d6efc28d60.r2.dev/2.pdf",
    "preview_page": "https://i.ibb.co.com/sb7rrPB/2.png",
    "language": "ru"
  },
  {
    "names": {
      "kk": "Шыныбеков АжАБ 10",
      "ru": "Шыныбеков АжАБ 10"
    },
    "group": "algebra",
    "image": "https://i.ibb.co.com/V3pmqN5/5.png",
    "pdf_url": "https://pub-6b4913ff96fe4b018ce574d6efc28d60.r2.dev/5.pdf",
    "preview_page": "https://i.ibb.co.com/V3pmqN5/5.png",
    "language": "ru"
  },
  {
    "names": {
      "kk": "Виленкина 9",
      "ru": "Виленкина 9"
    },
    "group": "algebra",
    "image": "https://i.ibb.co.com/R3SMCz7/7.png",
    "pdf_url": "https://pub-6b4913ff96fe4b018ce574d6efc28d60.r2.dev/7.pdf",
    "preview_page": "https://i.ibb.co.com/R3SMCz7/7.png",
    "language": "ru"
  },
  {
    "names": {
      "kk": "Первообразная и интеграл 11",
      "ru": "Первообразная и интеграл 11"
    },
    "group": "algebra",
    "image": "https://i.ibb.co.com/wMq0YyW/8.png",
    "pdf_url": "https://pub-6b4913ff96fe4b018ce574d6efc28d60.r2.dev/8.pdf",
    "preview_page": "https://i.ibb.co.com/wMq0YyW/8.png",
    "language": "ru"
  },
  {
    "names": {
      "kk": "Галицкий 7-9",
      "ru": "Галицкий 7-9"
    },
    "group": "algebra",
    "image": "https://i.ibb.co.com/pxBYn2d/9.png",
    "pdf_url": "https://pub-6b4913ff96fe4b018ce574d6efc28d60.r2.dev/A3.pdf",
    "preview_page": "https://i.ibb.co.com/pxBYn2d/9.png",
    "language": "ru"
  },
  {
    "names": {
      "kk": "В.Б. ГРАХОВ",
      "ru": "В.Б. ГРАХОВ"
    },
    "group": "algebra",
    "image": "https://i.ibb.co.com/Jp5wHQ8/10.png",
    "pdf_url": "https://pub-6b4913ff96fe4b018ce574d6efc28d60.r2.dev/10.pdf",
    "preview_page": "https://i.ibb.co.com/Jp5wHQ8/10.png",
    "language": "ru"
  },
  {
    "names": {
      "kk": "Махмеджанов",
      "ru": "Махмеджанов"
    },
    "group": "algebra",
    "image": "https://i.ibb.co.com/CQkVVnV/11.png",
    "pdf_url": "https://pub-6b4913ff96fe4b018ce574d6efc28d60.r2.dev/11.pdf",
    "preview_page": "https://i.ibb.co.com/CQkVVnV/11.png",
    "language": "ru"
  },
  {
    "names": {
      "kk": "Письменный",
      "ru": "Письменный"
    },
    "group": "algebra",
    "image": "https://i.ibb.co.com/MVFsccm/13.png",
    "pdf_url": "https://pub-6b4913ff96fe4b018ce574d6efc28d60.r2.dev/13.pdf",
    "preview_page": "https://i.ibb.co.com/MVFsccm/13.png",
    "language": "ru"
  },
  {
    "names": {
      "kk": "Шевкин 5-6",
      "ru": "Шевкин 5-6"
    },
    "group": "algebra",
    "image": "https://i.ibb.co.com/s6WLhsm/16.png",
    "pdf_url": "https://pub-6b4913ff96fe4b018ce574d6efc28d60.r2.dev/16.pdf",
    "preview_page": "https://i.ibb.co.com/s6WLhsm/16.png",
    "language": "ru"
  },
  {
    "names": {
      "kk": "Лобачевского",
      "ru": "Лобачевского"
    },
    "group": "algebra",
    "image": "https://i.ibb.co.com/pw3z9NL/17.png",
    "pdf_url": "https://pub-6b4913ff96fe4b018ce574d6efc28d60.r2.dev/17.pdf",
    "preview_page": "https://i.ibb.co.com/pw3z9NL/17.png",
    "language": "ru"
  },
  {
    "names": {
      "kk": "Виленкин",
      "ru": "Виленкин"
    },
    "group": "algebra",
    "image": "https://i.ibb.co.com/Yb0b8h8/18.png",
    "pdf_url": "https://pub-6b4913ff96fe4b018ce574d6efc28d60.r2.dev/18.pdf",
    "preview_page": "https://i.ibb.co.com/Yb0b8h8/18.png",
    "language": "ru"
  },
  {
    "names": {
      "kk": "Комбинаторика",
      "ru": "Комбинаторика"
    },
    "group": "algebra",
    "image": "https://i.ibb.co.com/Yb0b8h8/24.png",
    "pdf_url": "https://pub-6b4913ff96fe4b018ce574d6efc28d60.r2.dev/24.pdf",
    "preview_page": "https://i.ibb.co.com/Yb0b8h8/24.png",
    "language": "ru"
  },
  {
    "names": {
      "kk": "Лейбсон (1)",
      "ru": "Лейбсон (1)"
    },
    "group": "algebra",
    "image": "https://i.ibb.co.com/ZdJRLZJ/25.png",
    "pdf_url": "https://pub-6b4913ff96fe4b018ce574d6efc28d60.r2.dev/25.pdf",
    "preview_page": "https://i.ibb.co.com/ZdJRLZJ/25.png",
    "language": "ru"
  },
  {
    "names": {
      "kk": "Лейбсон (3)",
      "ru": "Лейбсон (3)"
    },
    "group": "algebra",
    "image": "https://i.ibb.co.com/8rRWRPm/26.png",
    "pdf_url": "https://pub-6b4913ff96fe4b018ce574d6efc28d60.r2.dev/26.pdf",
    "preview_page": "https://i.ibb.co.com/8rRWRPm/26.png",
    "language": "ru"
  },
  {
    "names": {
      "kk": "Лысенко 10-11",
      "ru": "Лысенко 10-11"
    },
    "group": "algebra",
    "image": "https://i.ibb.co.com/rkPxrZF/27.png",
    "pdf_url": "https://pub-6b4913ff96fe4b018ce574d6efc28d60.r2.dev/27.pdf",
    "preview_page": "https://i.ibb.co.com/rkPxrZF/27.png",
    "language": "ru"
  },
  {
    "names": {
      "kk": "Бусев 15 жылдық",
      "ru": "Бусев 15 жылдық"
    },
    "group": "algebra",
    "image": "https://i.ibb.co.com/vqJmZZD/28.png",
    "pdf_url": "https://pub-6b4913ff96fe4b018ce574d6efc28d60.r2.dev/28.pdf",
    "preview_page": "https://i.ibb.co.com/vqJmZZD/28.png",
    "language": "kk"
  },
  {
    "names": {
      "kk": "Чистякова 8",
      "ru": "Чистякова 8"
    },
    "group": "algebra",
    "image": "https://i.ibb.co.com/yn53krR/29.png",
    "pdf_url": "https://pub-6b4913ff96fe4b018ce574d6efc28d60.r2.dev/29.pdf",
    "preview_page": "https://i.ibb.co.com/yn53krR/29.png",
    "language": "ru"
  },
  {
    "names": {
      "kk": "Мерзляк 8-11",
      "ru": "Мерзляк 8-11"
    },
    "group": "algebra",
    "image": "https://i.ibb.co/2W1sphY/32.png",
    "pdf_url": "https://pub-6b4913ff96fe4b018ce574d6efc28d60.r2.dev/32.pdf",
    "preview_page": "https://i.ibb.co/2W1sphY/32.png",
    "language": "ru"
  },
  {
    "names": {
      "kk": "Шексіздік",
      "ru": "Шексіздік"
    },
    "group": "algebra",
    "image": "https://i.ibb.co.com/9NvRLGZ/36.png",
    "pdf_url": "https://pub-6b4913ff96fe4b018ce574d6efc28d60.r2.dev/36.pdf",
    "preview_page": "https://i.ibb.co.com/9NvRLGZ/36.png",
    "language": "kk"
  },
  {
    "names": {
      "kk": "Фалин",
      "ru": "Фалин"
    },
    "group": "algebra",
    "image": "https://i.ibb.co.com/88PNQJb/38.png",
    "pdf_url": "https://pub-6b4913ff96fe4b018ce574d6efc28d60.r2.dev/38.pdf",
    "preview_page": "https://i.ibb.co.com/88PNQJb/38.png",
    "language": "ru"
  },
  {
    "names": {
      "kk": "Шабунин 10-11",
      "ru": "Шабунин 10-11"
    },
    "group": "algebra",
    "image": "https://i.ibb.co.com/PQFX0Ls/39.png",
    "pdf_url": "https://pub-6b4913ff96fe4b018ce574d6efc28d60.r2.dev/39.pdf",
    "preview_page": "https://i.ibb.co.com/PQFX0Ls/39.png",
    "language": "ru"
  },
  {
    "names": {
      "kk": "Тригонометрия",
      "ru": "Тригонометрия"
    },
    "group": "Шахмейстер",
    "image": "https://i.ibb.co.com/jywL9zn/A22.png",
    "pdf_url": "https://pub-6b4913ff96fe4b018ce574d6efc28d60.r2.dev/A22.pdf",
    "preview_page": "https://i.ibb.co.com/jywL9zn/A22.png",
    "language": "ru"
  },
  {
    "names": {
      "kk": "Логарифмы",
      "ru": "Логарифмы"
    },
    "group": "Шахмейстер",
    "image": "https://i.ibb.co.com/dpYSDR9/A21.png",
    "pdf_url": "https://pub-6b4913ff96fe4b018ce574d6efc28d60.r2.dev/A21.pdf",
    "preview_page": "https://i.ibb.co.com/dpYSDR9/A21.png",
    "language": "ru"
  },
  {
    "names": {
      "kk": "Геометрические задачи (Часть 2-3)",
      "ru": "Геометрические задачи (Часть 2-3)"
    },
    "group": "Шахмейстер",
    "image": "https://i.ibb.co.com/sCS7yn9/A19.png",
    "pdf_url": "https://pub-6b4913ff96fe4b018ce574d6efc28d60.r2.dev/A19.pdf",
    "preview_page": "https://i.ibb.co.com/sCS7yn9/A19.png",
    "language": "ru"
  },
  {
    "names": {
      "kk": "Геометрические задачи (Часть 1)",
      "ru": "Геометрические задачи (Часть 1)"
    },
    "group": "Шахмейстер",
    "image": "https://i.ibb.co.com/0nYrHhy/A18.png",
    "pdf_url": "https://pub-6b4913ff96fe4b018ce574d6efc28d60.r2.dev/A18.pdf",
    "preview_page": "https://i.ibb.co.com/0nYrHhy/A18.png",
    "language": "ru"
  },
  {
    "names": {
      "kk": "Доказательство неравенств. Матем. индукция",
      "ru": "Доказательство неравенств. Матем. индукция"
    },
    "group": "Шахмейстер",
    "image": "https://i.ibb.co.com/gF0L8L6/A16.png",
    "pdf_url": "https://pub-6b4913ff96fe4b018ce574d6efc28d60.r2.dev/A16.pdf",
    "preview_page": "https://i.ibb.co.com/gF0L8L6/A16.png",
    "language": "ru"
  },
  {
    "names": {
      "kk": "Множества, Функции, Последовательности",
      "ru": "Множества, Функции, Последовательности"
    },
    "group": "Шахмейстер",
    "image": "https://i.ibb.co.com/hFYVv9L/A15.png",
    "pdf_url": "https://pub-6b4913ff96fe4b018ce574d6efc28d60.r2.dev/A15.pdf",
    "preview_page": "https://i.ibb.co.com/hFYVv9L/A15.png",
    "language": "ru"
  },
  {
    "names": {
      "kk": "Построение графиков. Параметры (ч.1)",
      "ru": "Построение графиков. Параметры (ч.1)"
    },
    "group": "Шахмейстер",
    "image": "https://i.ibb.co.com/qMMqK0R/A13.png",
    "pdf_url": "https://pub-6b4913ff96fe4b018ce574d6efc28d60.r2.dev/A13.pdf",
    "preview_page": "https://i.ibb.co.com/qMMqK0R/A13.png",
    "language": "ru"
  },
  {
    "names": {
      "kk": "Построение графиков. Параметры (ч.2-3)",
      "ru": "Построение графиков. Параметры (ч.2-3)"
    },
    "group": "Шахмейстер",
    "image": "https://i.ibb.co.com/s3njXpj/A12.png",
    "pdf_url": "https://pub-6b4913ff96fe4b018ce574d6efc28d60.r2.dev/A12.pdf",
    "preview_page": "https://i.ibb.co.com/s3njXpj/A12.png",
    "language": "ru"
  },
  {
    "names": {
      "kk": "Введение в МатАн",
      "ru": "Введение в МатАн"
    },
    "group": "Шахмейстер",
    "image": "https://i.ibb.co.com/zfNWm6M/A10.png",
    "pdf_url": "https://pub-6b4913ff96fe4b018ce574d6efc28d60.r2.dev/A10.pdf",
    "preview_page": "https://i.ibb.co.com/zfNWm6M/A10.png",
    "language": "ru"
  },
  {
    "names": {
      "kk": "Комплексные числа",
      "ru": "Комплексные числа"
    },
    "group": "Шахмейстер",
    "image": "https://i.ibb.co.com/zfNWm6M/A9.png",
    "pdf_url": "https://pub-6b4913ff96fe4b018ce574d6efc28d60.r2.dev/A9.pdf",
    "preview_page": "https://i.ibb.co.com/zfNWm6M/A9.png",
    "language": "ru"
  },
  {
    "names": {
      "kk": "Системы уравнений",
      "ru": "Системы уравнений"
    },
    "group": "Шахмейстер",
    "image": "https://i.ibb.co.com/zfNWm6M/A8.png",
    "pdf_url": "https://pub-6b4913ff96fe4b018ce574d6efc28d60.r2.dev/A8.pdf",
    "preview_page": "https://i.ibb.co.com/zfNWm6M/A8.png",
    "language": "ru"
  },
  {
    "names": {
      "kk": "Иррациональные уравнения",
      "ru": "Иррациональные уравнения"
    },
    "group": "Шахмейстер",
    "image": "https://i.ibb.co.com/zfNWm6M/A7.png",
    "pdf_url": "https://pub-6b4913ff96fe4b018ce574d6efc28d60.r2.dev/A7.pdf",
    "preview_page": "https://i.ibb.co.com/zfNWm6M/A7.png",
    "language": "ru"
  },
  {
    "names": {
      "kk": "Корни",
      "ru": "Корни"
    },
    "group": "Шахмейстер",
    "image": "https://i.ibb.co.com/zfNWm6M/A6.png",
    "pdf_url": "https://pub-6b4913ff96fe4b018ce574d6efc28d60.r2.dev/A6.pdf",
    "preview_page": "https://i.ibb.co.com/zfNWm6M/A6.png",
    "language": "ru"
  },
  {
    "names": {
      "kk": "Дроби",
      "ru": "Дроби"
    },
    "group": "Шахмейстер",
    "image": "https://i.ibb.co.com/zfNWm6M/A5.png",
    "pdf_url": "https://pub-6b4913ff96fe4b018ce574d6efc28d60.r2.dev/A5.pdf",
    "preview_page": "https://i.ibb.co.com/zfNWm6M/A5.png",
    "language": "ru"
  },
  {
    "names": {
      "kk": "Дробно рациональные неравенства",
      "ru": "Дробно рациональные неравенства"
    },
    "group": "Шахмейстер",
    "image": "https://i.ibb.co.com/zfNWm6M/A4.png",
    "pdf_url": "https://pub-6b4913ff96fe4b018ce574d6efc28d60.r2.dev/A4.pdf",
    "preview_page": "https://i.ibb.co.com/zfNWm6M/A4.png",
    "language": "ru"
  },
  {
    "names": {
      "ru": "Қазақ тілі мен әдебиеті 1",
      "kk": "Қазақ тілі мен әдебиеті 1"
    },
    "group": "7",
    "image": "https://books.okulyk.kz/258/258.jpg",
    "pdf_url": "https://books.okulyk.kz/258/258.pdf",
    "preview_page": "",
    "language": "ru"
  },
  {
    "names": {
      "ru": "Қазақ тілі мен әдебиеті 2",
      "kk": "Қазақ тілі мен әдебиеті 2"
    },
    "group": "7",
    "image": "https://books.okulyk.kz/259/259.jpg",
    "pdf_url": "https://books.okulyk.kz/259/259.pdf",
    "preview_page": "",
    "language": "ru"
  },
  {
    "names": {
      "ru": "Русская литература",
      "kk": "Орыс әдебиеті"
    },
    "group": "7",
    "image": "https://books.okulyk.kz/1511/1511.jpg",
    "pdf_url": "https://books.okulyk.kz/1511/1511.pdf",
    "preview_page": "",
    "language": "ru"
  },
  {
    "names": {
      "ru": "Алгебра",
      "kk": "Алгебра"
    },
    "group": "7",
    "image": "https://books.okulyk.kz/1512/1512.jpg",
    "pdf_url": "https://books.okulyk.kz/1512/1512.pdf",
    "preview_page": "",
    "language": "ru"
  },
  {
    "names": {
      "ru": "Геометрия",
      "kk": "Геометрия"
    },
    "group": "7",
    "image": "https://books.okulyk.kz/1514/1514.jpg",
    "pdf_url": "https://books.okulyk.kz/1514/1514.pdf",
    "preview_page": "",
    "language": "ru"
  },
  {
    "names": {
      "ru": "Физика",
      "kk": "Физика"
    },
    "group": "7",
    "image": "https://books.okulyk.kz/1522/1522.jpg",
    "pdf_url": "https://books.okulyk.kz/1522/1522.pdf",
    "preview_page": "",
    "language": "ru"
  },
  {
    "names": {
      "ru": "Химия",
      "kk": "Химия"
    },
    "group": "7",
    "image": "https://books.okulyk.kz/1063/1063.jpg",
    "pdf_url": "https://books.okulyk.kz/1063/1063.pdf",
    "preview_page": "",
    "language": "ru"
  },
  {
    "names": {
      "ru": "Биология",
      "kk": "Биология"
    },
    "group": "7",
    "image": "https://books.okulyk.kz/1519/1519.jpg",
    "pdf_url": "https://books.okulyk.kz/1519/1519.pdf",
    "preview_page": "",
    "language": "ru"
  },
  {
    "names": {
      "ru": "Информатика",
      "kk": "Информатика"
    },
    "group": "7",
    "image": "https://books.okulyk.kz/1289/1289.jpg",
    "pdf_url": "https://books.okulyk.kz/1289/1289.pdf",
    "preview_page": "",
    "language": "ru"
  },
  {
    "names": {
      "ru": "История Казахстана",
      "kk": "Қазақстан тарихы"
    },
    "group": "7",
    "image": "https://books.okulyk.kz/1525/1525.jpg",
    "pdf_url": "https://books.okulyk.kz/1525/1525.pdf",
    "preview_page": "",
    "language": "ru"
  },
  {
    "names": {
      "ru": "Всемирная история",
      "kk": "Дүниежүзі тарихы"
    },
    "group": "7",
    "image": "https://books.okulyk.kz/1042/1042.jpg",
    "pdf_url": "https://books.okulyk.kz/1042/1042.pdf",
    "preview_page": "",
    "language": "ru"
  },
  {
    "names": {
      "ru": "География",
      "kk": "География"
    },
    "group": "7",
    "image": "https://books.okulyk.kz/1516/1516.jpg",
    "pdf_url": "https://books.okulyk.kz/1516/1516.pdf",
    "preview_page": "",
    "language": "ru"
  },
  {
    "names": {
      "ru": "Английский язык",
      "kk": "Ағылшын тілі"
    },
    "group": "7",
    "image": "https://books.okulyk.kz/286/286.jpg",
    "pdf_url": "https://books.okulyk.kz/286/286.pdf",
    "preview_page": "",
    "language": "ru"
  },
  {
    "names": {
      "ru": "Қазақ тілі мен әдебиеті 1",
      "kk": "Қазақ тілі мен әдебиеті 1"
    },
    "group": "8",
    "image": "https://books.okulyk.kz/768/768.jpg",
    "pdf_url": "https://books.okulyk.kz/768/768.pdf",
    "preview_page": "",
    "language": "ru"
  },
  {
    "names": {
      "ru": "Қазақ тілі мен әдебиеті 2",
      "kk": "Қазақ тілі мен әдебиеті 2"
    },
    "group": "8",
    "image": "https://books.okulyk.kz/769/769.jpg",
    "pdf_url": "https://books.okulyk.kz/769/769.pdf",
    "preview_page": "",
    "language": "ru"
  },
  {
    "names": {
      "ru": "Русский язык",
      "kk": "Орыс тілі"
    },
    "group": "8",
    "image": "https://books.okulyk.kz/331/331.jpg",
    "pdf_url": "https://books.okulyk.kz/331/331.pdf",
    "preview_page": "",
    "language": "ru"
  },
  {
    "names": {
      "ru": "Русская литература",
      "kk": "Орыс әдебиеті"
    },
    "group": "8",
    "image": "https://books.okulyk.kz/334/334.jpg",
    "pdf_url": "https://books.okulyk.kz/334/334.pdf",
    "preview_page": "",
    "language": "ru"
  },
  {
    "names": {
      "ru": "Алгебра",
      "kk": "Алгебра"
    },
    "group": "8",
    "image": "https://books.okulyk.kz/335/335.jpg",
    "pdf_url": "https://books.okulyk.kz/335/335.pdf",
    "preview_page": "",
    "language": "ru"
  },
  {
    "names": {
      "ru": "Геометрия",
      "kk": "Геометрия"
    },
    "group": "8",
    "image": "https://books.okulyk.kz/338/338.jpg",
    "pdf_url": "https://books.okulyk.kz/338/338.pdf",
    "preview_page": "",
    "language": "ru"
  },
  {
    "names": {
      "ru": "Физика",
      "kk": "Физика"
    },
    "group": "8",
    "image": "https://books.okulyk.kz/348/348.jpg",
    "pdf_url": "https://books.okulyk.kz/348/348.pdf",
    "preview_page": "",
    "language": "ru"
  },
  {
    "names": {
      "ru": "Химия",
      "kk": "Химия"
    },
    "group": "8",
    "image": "https://books.okulyk.kz/349/349.jpg",
    "pdf_url": "https://books.okulyk.kz/349/349.pdf",
    "preview_page": "",
    "language": "ru"
  },
  {
    "names": {
      "ru": "Биология",
      "kk": "Биология"
    },
    "group": "8",
    "image": "https://books.okulyk.kz/346/346.jpg",
    "pdf_url": "https://books.okulyk.kz/346/346.pdf",
    "preview_page": "",
    "language": "ru"
  },
  {
    "names": {
      "ru": "Информатика",
      "kk": "Информатика"
    },
    "group": "8",
    "image": "https://books.okulyk.kz/949/949.jpg",
    "pdf_url": "https://books.okulyk.kz/949/949.pdf",
    "preview_page": "",
    "language": "ru"
  },
  {
    "names": {
      "ru": "История Казахстана",
      "kk": "Қазақстан тарихы"
    },
    "group": "8",
    "image": "https://books.okulyk.kz/1533/1533.jpg",
    "pdf_url": "https://books.okulyk.kz/1533/1533.pdf",
    "preview_page": "",
    "language": "ru"
  },
  {
    "names": {
      "ru": "Всемирная история",
      "kk": "Дүниежүзі тарихы"
    },
    "group": "8",
    "image": "https://books.okulyk.kz/1071/1071.jpg",
    "pdf_url": "https://books.okulyk.kz/1071/1071.pdf",
    "preview_page": "",
    "language": "ru"
  },
  {
    "names": {
      "ru": "География",
      "kk": "География"
    },
    "group": "8",
    "image": "https://books.okulyk.kz/1298/1298.jpg",
    "pdf_url": "https://books.okulyk.kz/1298/1298.pdf",
    "preview_page": "",
    "language": "ru"
  },
  {
    "names": {
      "ru": "Английский язык",
      "kk": "Ағылшын тілі"
    },
    "group": "8",
    "image": "https://books.okulyk.kz/362/362.jpg",
    "pdf_url": "https://books.okulyk.kz/362/362.pdf",
    "preview_page": "",
    "language": "ru"
  },
  {
    "names": {
      "ru": "Қазақ тілі мен әдебиеті 1",
      "kk": "Қазақ тілі мен әдебиеті 1"
    },
    "group": "9",
    "image": "https://books.okulyk.kz/433/433.jpg",
    "pdf_url": "https://books.okulyk.kz/433/433.pdf",
    "preview_page": "",
    "language": "ru"
  },
  {
    "names": {
      "ru": "Қазақ тілі мен әдебиеті 2",
      "kk": "Қазақ тілі мен әдебиеті 2"
    },
    "group": "9",
    "image": "https://books.okulyk.kz/434/434.jpg",
    "pdf_url": "https://books.okulyk.kz/434/434.pdf",
    "preview_page": "",
    "language": "ru"
  },
  {
    "names": {
      "ru": "Русский язык",
      "kk": "Орыс тілі"
    },
    "group": "9",
    "image": "https://books.okulyk.kz/427/427.jpg",
    "pdf_url": "https://books.okulyk.kz/427/427.pdf",
    "preview_page": "",
    "language": "ru"
  },
  {
    "names": {
      "ru": "Русская литература",
      "kk": "Орыс әдебиеті"
    },
    "group": "9",
    "image": "https://books.okulyk.kz/428/428.jpg",
    "pdf_url": "https://books.okulyk.kz/428/428.pdf",
    "preview_page": "",
    "language": "ru"
  },
  {
    "names": {
      "ru": "Алгебра",
      "kk": "Алгебра"
    },
    "group": "9",
    "image": "https://books.okulyk.kz/436/436.jpg",
    "pdf_url": "https://books.okulyk.kz/436/436.pdf",
    "preview_page": "",
    "language": "ru"
  },
  {
    "names": {
      "ru": "Геометрия",
      "kk": "Геометрия"
    },
    "group": "9",
    "image": "https://books.okulyk.kz/437/437.jpg",
    "pdf_url": "https://books.okulyk.kz/437/437.pdf",
    "preview_page": "",
    "language": "ru"
  },
  {
    "names": {
      "ru": "Физика",
      "kk": "Физика"
    },
    "group": "9",
    "image": "https://books.okulyk.kz/451/451.jpg",
    "pdf_url": "https://books.okulyk.kz/451/451.pdf",
    "preview_page": "",
    "language": "ru"
  },
  {
    "names": {
      "ru": "Химия",
      "kk": "Химия"
    },
    "group": "9",
    "image": "https://books.okulyk.kz/454/454.jpg",
    "pdf_url": "https://books.okulyk.kz/454/454.pdf",
    "preview_page": "",
    "language": "ru"
  },
  {
    "names": {
      "ru": "Биология",
      "kk": "Биология"
    },
    "group": "9",
    "image": "https://books.okulyk.kz/450/450.jpg",
    "pdf_url": "https://books.okulyk.kz/450/450.pdf",
    "preview_page": "",
    "language": "ru"
  },
  {
    "names": {
      "ru": "Информатика",
      "kk": "Информатика"
    },
    "group": "9",
    "image": "https://books.okulyk.kz/1089/1089.jpg",
    "pdf_url": "https://books.okulyk.kz/1089/1089.pdf",
    "preview_page": "",
    "language": "ru"
  },
  {
    "names": {
      "ru": "История Казахстана 1",
      "kk": "Қазақстан тарихы 1"
    },
    "group": "9",
    "image": "https://books.okulyk.kz/460/460.jpg",
    "pdf_url": "https://books.okulyk.kz/460/460.pdf",
    "preview_page": "",
    "language": "ru"
  },
  {
    "names": {
      "ru": "История Казахстана 2",
      "kk": "Қазақстан тарихы 2"
    },
    "group": "9",
    "image": "https://books.okulyk.kz/461/461.jpg",
    "pdf_url": "https://books.okulyk.kz/461/461.pdf",
    "preview_page": "",
    "language": "ru"
  },
  {
    "names": {
      "ru": "Всемирная история",
      "kk": "Дүниежүзі тарихы"
    },
    "group": "9",
    "image": "https://books.okulyk.kz/1087/1087.jpg",
    "pdf_url": "https://books.okulyk.kz/1087/1087.pdf",
    "preview_page": "",
    "language": "ru"
  },
  {
    "names": {
      "ru": "География 1",
      "kk": "География 1"
    },
    "group": "9",
    "image": "https://books.okulyk.kz/1186/1186.jpg",
    "pdf_url": "https://books.okulyk.kz/1186/1186.pdf",
    "preview_page": "",
    "language": "ru"
  },
  {
    "names": {
      "ru": "География 2",
      "kk": "География 2"
    },
    "group": "9",
    "image": "https://books.okulyk.kz/1187/1187.jpg",
    "pdf_url": "https://books.okulyk.kz/1187/1187.pdf",
    "preview_page": "",
    "language": "ru"
  },
  {
    "names": {
      "ru": "Английский язык",
      "kk": "Ағылшын тілі"
    },
    "group": "9",
    "image": "https://books.okulyk.kz/469/469.jpg",
    "pdf_url": "https://books.okulyk.kz/469/469.pdf",
    "preview_page": "",
    "language": "ru"
  },
  {
    "names": {
      "ru": "Қазақ тілі мен әдебиеті 1",
      "kk": "Қазақ тілі мен әдебиеті 1"
    },
    "group": "10",
    "image": "https://books.okulyk.kz/607/607.jpg",
    "pdf_url": "https://books.okulyk.kz/607/607.pdf",
    "preview_page": "",
    "language": "ru"
  },
  {
    "names": {
      "ru": "Қазақ тілі мен әдебиеті 2",
      "kk": "Қазақ тілі мен әдебиеті 2"
    },
    "group": "10",
    "image": "https://books.okulyk.kz/608/608.jpg",
    "pdf_url": "https://books.okulyk.kz/608/608.pdf",
    "preview_page": "",
    "language": "ru"
  },
  {
    "names": {
      "ru": "Русский язык",
      "kk": "Орыс тілі"
    },
    "group": "10",
    "image": "https://books.okulyk.kz/511/511.jpg",
    "pdf_url": "https://books.okulyk.kz/511/511.pdf",
    "preview_page": "",
    "language": "ru"
  },
  {
    "names": {
      "ru": "Русская литература 1",
      "kk": "Орыс әдебиеті 1"
    },
    "group": "10",
    "image": "https://books.okulyk.kz/569/569.jpg",
    "pdf_url": "https://books.okulyk.kz/569/569.pdf",
    "preview_page": "",
    "language": "ru"
  },
  {
    "names": {
      "ru": "Русская литература 2",
      "kk": "Орыс әдебиеті 2"
    },
    "group": "10",
    "image": "https://books.okulyk.kz/514/514.jpg",
    "pdf_url": "https://books.okulyk.kz/514/514.pdf",
    "preview_page": "",
    "language": "ru"
  },
  {
    "names": {
      "ru": "Алгебра (Шыныбеков)",
      "kk": "Алгебра"
    },
    "group": "10",
    "image": "https://books.okulyk.kz/515/515.jpg",
    "pdf_url": "https://books.okulyk.kz/515/515.pdf",
    "preview_page": "",
    "language": "ru"
  },
  {
    "names": {
      "ru": "Геометрия (Шыныбеков)",
      "kk": "Геометрия"
    },
    "group": "10",
    "image": "https://books.okulyk.kz/516/516.jpg",
    "pdf_url": "https://books.okulyk.kz/516/516.pdf",
    "preview_page": "",
    "language": "ru"
  },
  {
    "names": {
      "ru": "Физика 1",
      "kk": "Физика 1"
    },
    "group": "10",
    "image": "https://books.okulyk.kz/531/531.jpg",
    "pdf_url": "https://books.okulyk.kz/531/531.pdf",
    "preview_page": "",
    "language": "ru"
  },
  {
    "names": {
      "ru": "Физика 2",
      "kk": "Физика 2"
    },
    "group": "10",
    "image": "https://books.okulyk.kz/580/580.jpg",
    "pdf_url": "https://books.okulyk.kz/580/580.pdf",
    "preview_page": "",
    "language": "ru"
  },
  {
    "names": {
      "ru": "Биология",
      "kk": "Биология"
    },
    "group": "10",
    "image": "https://books.okulyk.kz/578/578.jpg",
    "pdf_url": "https://books.okulyk.kz/578/578.pdf",
    "preview_page": "",
    "language": "ru"
  },
  {
    "names": {
      "ru": "Информатика",
      "kk": "Информатика"
    },
    "group": "10",
    "image": "https://books.okulyk.kz/521/521.jpg",
    "pdf_url": "https://books.okulyk.kz/521/521.pdf",
    "preview_page": "",
    "language": "ru"
  },
  {
    "names": {
      "ru": "География 1",
      "kk": "География 1"
    },
    "group": "10",
    "image": "https://books.okulyk.kz/524/524.jpg",
    "pdf_url": "https://books.okulyk.kz/524/524.pdf",
    "preview_page": "",
    "language": "ru"
  },
  {
    "names": {
      "ru": "География 2",
      "kk": "География 2"
    },
    "group": "10",
    "image": "https://books.okulyk.kz/525/525.jpg",
    "pdf_url": "https://books.okulyk.kz/525/525.pdf",
    "preview_page": "",
    "language": "ru"
  },
  {
    "names": {
      "ru": "НВП 1",
      "kk": "НВП 1"
    },
    "group": "10",
    "image": "https://books.okulyk.kz/613/613.jpg",
    "pdf_url": "https://books.okulyk.kz/613/613.pdf",
    "preview_page": "",
    "language": "ru"
  },
  {
    "names": {
      "ru": "НВП 2",
      "kk": "НВП 2"
    },
    "group": "10",
    "image": "https://books.okulyk.kz/614/614.jpg",
    "pdf_url": "https://books.okulyk.kz/614/614.pdf",
    "preview_page": "",
    "language": "ru"
  },
  {
    "names": {
      "ru": "Английский язык",
      "kk": "Ағылшын тілі"
    },
    "group": "10",
    "image": "https://books.okulyk.kz/535/535.jpg",
    "pdf_url": "https://books.okulyk.kz/535/535.pdf",
    "preview_page": "",
    "language": "ru"
  },
  {
    "names": {
      "ru": "Қазақ тілі мен әдебиеті 1",
      "kk": "Қазақ тілі мен әдебиеті 1"
    },
    "group": "11",
    "image": "https://books.okulyk.kz/790/790.jpg",
    "pdf_url": "https://books.okulyk.kz/790/790.pdf",
    "preview_page": "",
    "language": "ru"
  },
  {
    "names": {
      "ru": "Қазақ тілі мен әдебиеті 2",
      "kk": "Қазақ тілі мен әдебиеті 2"
    },
    "group": "11",
    "image": "https://books.okulyk.kz/791/791.jpg",
    "pdf_url": "https://books.okulyk.kz/791/791.pdf",
    "preview_page": "",
    "language": "ru"
  },
  {
    "names": {
      "ru": "Русский язык",
      "kk": "Орыс тілі"
    },
    "group": "11",
    "image": "https://books.okulyk.kz/799/799.jpg",
    "pdf_url": "https://books.okulyk.kz/799/799.pdf",
    "preview_page": "",
    "language": "ru"
  },
  {
    "names": {
      "ru": "Русская литература 1",
      "kk": "Орыс әдебиеті 1"
    },
    "group": "11",
    "image": "https://books.okulyk.kz/794/794.jpg",
    "pdf_url": "https://books.okulyk.kz/794/794.pdf",
    "preview_page": "",
    "language": "ru"
  },
  {
    "names": {
      "ru": "Русская литература 2",
      "kk": "Орыс әдебиеті 2"
    },
    "group": "11",
    "image": "https://books.okulyk.kz/795/795.jpg",
    "pdf_url": "https://books.okulyk.kz/795/795.pdf",
    "preview_page": "",
    "language": "ru"
  },
  {
    "names": {
      "ru": "Рус. лит. Хрестоматия 1",
      "kk": "Орыс лит. хрестоматия 1"
    },
    "group": "11",
    "image": "https://books.okulyk.kz/1119/1119.jpg",
    "pdf_url": "https://books.okulyk.kz/1119/1119.pdf",
    "preview_page": "",
    "language": "ru"
  },
  {
    "names": {
      "ru": "Рус. лит. Хрестоматия 2",
      "kk": "Орыс лит. хрестоматия 2"
    },
    "group": "11",
    "image": "https://books.okulyk.kz/1120/1120.jpg",
    "pdf_url": "https://books.okulyk.kz/1120/1120.pdf",
    "preview_page": "",
    "language": "ru"
  },
  {
    "names": {
      "ru": "Алгебра 1 (Шыныбеков)",
      "kk": "Алгебра 1"
    },
    "group": "11",
    "image": "https://books.okulyk.kz/779/779.jpg",
    "pdf_url": "https://books.okulyk.kz/779/779.pdf",
    "preview_page": "",
    "language": "ru"
  },
  {
    "names": {
      "ru": "Алгебра 2 (Шыныбеков)",
      "kk": "Алгебра 2"
    },
    "group": "11",
    "image": "https://books.okulyk.kz/780/780.jpg",
    "pdf_url": "https://books.okulyk.kz/780/780.pdf",
    "preview_page": "",
    "language": "ru"
  },
  {
    "names": {
      "ru": "Геометрия (Шыныбеков)",
      "kk": "Геометрия"
    },
    "group": "11",
    "image": "https://books.okulyk.kz/824/824.jpg",
    "pdf_url": "https://books.okulyk.kz/824/824.pdf",
    "preview_page": "",
    "language": "ru"
  },
  {
    "names": {
      "ru": "Биология 1",
      "kk": "Биология 1"
    },
    "group": "11",
    "image": "https://okulyk.kz/wp-content/books/702/",
    "pdf_url": "https://okulyk.kz/wp-content/books/702/",
    "preview_page": "",
    "language": "ru"
  },
  {
    "names": {
      "ru": "Биология 2",
      "kk": "Биология 2"
    },
    "group": "11",
    "image": "https://books.okulyk.kz/713/713.jpg",
    "pdf_url": "https://books.okulyk.kz/713/713.pdf",
    "preview_page": "",
    "language": "ru"
  },
  {
    "names": {
      "ru": "Физика 1",
      "kk": "Физика 1"
    },
    "group": "11",
    "image": "https://okulyk.kz/wp-content/books/704/",
    "pdf_url": "https://okulyk.kz/wp-content/books/704/",
    "preview_page": "",
    "language": "ru"
  },
  {
    "names": {
      "ru": "Физика 2",
      "kk": "Физика 2"
    },
    "group": "11",
    "image": "https://okulyk.kz/wp-content/books/714/",
    "pdf_url": "https://okulyk.kz/wp-content/books/714/",
    "preview_page": "",
    "language": "ru"
  },
  {
    "names": {
      "ru": "Химия 1 (Оспанова)",
      "kk": "Химия 1"
    },
    "group": "11",
    "image": "https://okulyk.kz/wp-content/books/706/",
    "pdf_url": "https://okulyk.kz/wp-content/books/706/",
    "preview_page": "",
    "language": "ru"
  },
  {
    "names": {
      "ru": "Химия 2 (Оспанова)",
      "kk": "Химия 2"
    },
    "group": "11",
    "image": "https://okulyk.kz/wp-content/books/715/",
    "pdf_url": "https://okulyk.kz/wp-content/books/715/",
    "preview_page": "",
    "language": "ru"
  },
  {
    "names": {
      "ru": "История Казахстана 1",
      "kk": "Қазақстан тарихы 1"
    },
    "group": "11",
    "image": "https://books.okulyk.kz/827/827.jpg",
    "pdf_url": "https://books.okulyk.kz/827/827.pdf",
    "preview_page": "",
    "language": "ru"
  },
  {
    "names": {
      "ru": "История Казахстана 2",
      "kk": "Қазақстан тарихы 2"
    },
    "group": "11",
    "image": "https://books.okulyk.kz/828/828.jpg",
    "pdf_url": "https://books.okulyk.kz/828/828.pdf",
    "preview_page": "",
    "language": "ru"
  },
  {
    "names": {
      "ru": "Всемирная история",
      "kk": "Дүниежүзі тарихы"
    },
    "group": "11",
    "image": "https://okulyk.kz/wp-content/books/694/",
    "pdf_url": "https://okulyk.kz/wp-content/books/694/",
    "preview_page": "",
    "language": "ru"
  },
  {
    "names": {
      "ru": "География (Каймулдина)",
      "kk": "География"
    },
    "group": "11",
    "image": "https://okulyk.kz/wp-content/books/696/",
    "pdf_url": "https://okulyk.kz/wp-content/books/696/",
    "preview_page": "",
    "language": "ru"
  },
  {
    "names": {
      "ru": "Основы права (Ибраева)",
      "kk": "Құқық негізі"
    },
    "group": "11",
    "image": "https://okulyk.kz/wp-content/books/698/",
    "pdf_url": "https://okulyk.kz/wp-content/books/698/",
    "preview_page": "",
    "language": "ru"
  },
  {
    "names": {
      "ru": "НВП 1",
      "kk": "НВП 1"
    },
    "group": "11",
    "image": "https://books.okulyk.kz/1543/1543.jpg",
    "pdf_url": "https://books.okulyk.kz/1543/1543.pdf",
    "preview_page": "",
    "language": "ru"
  },
  {
    "names": {
      "ru": "НВП 2",
      "kk": "НВП 2"
    },
    "group": "11",
    "image": "https://books.okulyk.kz/1544/1544.jpg",
    "pdf_url": "https://books.okulyk.kz/1544/1544.pdf",
    "preview_page": "",
    "language": "ru"
  },
  {
    "names": {
      "ru": "Action for Kazakhstan SB",
      "kk": "Ағылшын тілі (SB)"
    },
    "group": "11",
    "image": "https://books.okulyk.kz/829/829.jpg",
    "pdf_url": "https://books.okulyk.kz/829/829.pdf",
    "preview_page": "",
    "language": "ru"
  },
  {
    "names": {
      "ru": "Action Workbook",
      "kk": "Ағылшын тілі (WB)"
    },
    "group": "11",
    "image": "https://books.okulyk.kz/830/830.jpg",
    "pdf_url": "https://books.okulyk.kz/830/830.pdf",
    "preview_page": "",
    "language": "ru"
  }
]